KolejkaWorker-0.1.202310121859-nspkg.pth
kolejka/worker/__init__.py
kolejka/worker/__nonpath__.py
kolejka/worker/create_alpine_python3_volume.sh
kolejka/worker/stage0.py
kolejka/worker/stage1.sh
kolejka/worker/stage2.py
kolejka/worker/volume.py
KolejkaWorker-0.1.202310121859.dist-info/METADATA
KolejkaWorker-0.1.202310121859.dist-info/WHEEL
KolejkaWorker-0.1.202310121859.dist-info/entry_points.txt
KolejkaWorker-0.1.202310121859.dist-info/namespace_packages.txt
KolejkaWorker-0.1.202310121859.dist-info/top_level.txt
KolejkaWorker-0.1.202310121859.dist-info/RECORD
